pyhades/__init__.py
pyhades/_singleton.py
pyhades/context.py
pyhades/core.py
pyhades/models.py
pyhades/state_machine.py
pyhades/status_codes.py
pyhades/alarms/__init__.py
pyhades/alarms/alarms.py
pyhades/alarms/states.py
pyhades/alarms/trigger.py
pyhades/dbmodels/__init__.py
pyhades/dbmodels/alarms.py
pyhades/dbmodels/core.py
pyhades/dbmodels/tags.py
pyhades/examples/__init__.py
pyhades/examples/alarm_management_system.py
pyhades/examples/data_acquisition_system.py
pyhades/logger/__init__.py
pyhades/logger/datalogger.py
pyhades/logger/engine.py
pyhades/logger/logdict.py
pyhades/logger/query.py
pyhades/managers/__init__.py
pyhades/managers/alarms.py
pyhades/managers/logger.py
pyhades/managers/state_machine.py
pyhades/src/__init__.py
pyhades/src/units.json
pyhades/src/variables.json
pyhades/tags/__init__.py
pyhades/tags/cvt.py
pyhades/tags/tag.py
pyhades/tags/tag_binding.py
pyhades/tags/tag_value.py
pyhades/tags/unit_conversion.py
pyhades/tests/__init__.py
pyhades/tests/test_alarm_manager.py
pyhades/tests/test_alarm_states.py
pyhades/tests/test_bool_alarms.py
pyhades/tests/test_dbmodels.py
pyhades/tests/test_dbmodels_from_config_file.py
pyhades/tests/test_high_alarms.py
pyhades/tests/test_high_high_alarms.py
pyhades/tests/test_low_alarms.py
pyhades/tests/test_low_low_alarms.py
pyhades/tests/test_unit_conversion.py
pyhades/tests/test_unit_conversion_from_tags.py
pyhades/utils/__init__.py
pyhades/utils/_errors.py
pyhades/utils/inspect.py
pyhades/utils/observer.py
pyhades/utils/others.py
pyhades/workers/__init__.py
pyhades/workers/alarms.py
pyhades/workers/continuos.py
pyhades/workers/logger.py
pyhades/workers/state_machine.py
pyhades/workers/worker.py
PyHades-0.2.1.dist-info/LICENSE
PyHades-0.2.1.dist-info/METADATA
PyHades-0.2.1.dist-info/WHEEL
PyHades-0.2.1.dist-info/top_level.txt
PyHades-0.2.1.dist-info/RECORD
