Metadata-Version: 2.1
Name: PyHades
Version: 0.2.1
Summary: A python library to develop automation continuous tasks using sync or async concurrent threads
Home-page: https://github.com/know-ai/hades
Author: KnowAI
Author-email: dev.know.ai@gmail.com
License: GNU AFFERO GENERAL PUBLIC LICENSE
Platform: UNKNOWN
Classifier: Programming Language :: Python :: 3.7
Classifier: Programming Language :: Python :: 3.8
Classifier: Programming Language :: Python :: 3.9
Classifier: Programming Language :: Python :: 3.10
Classifier: License :: OSI Approved :: GNU Affero General Public License v3
Classifier: Operating System :: OS Independent
Classifier: Topic :: Software Development :: Libraries
Classifier: Topic :: System :: Logging
Classifier: Topic :: System :: Monitoring
Requires-Dist: PyYAML (==6.0)
Requires-Dist: peewee (==3.14.10)
Requires-Dist: python-dotenv (==0.20.0)
Requires-Dist: python-statemachine (==0.8.0)
Requires-Dist: requests (==2.28.1)
Requires-Dist: tqdm (==4.50.2)
Requires-Dist: psycopg2-binary (==2.9.3) ; sys_platform != "win32"
Requires-Dist: psycopg2 (==2.9.3) ; sys_platform == "win32"
